verax/__init__.py
verax/verax.py
verax-0.0.1.dist-info/METADATA
verax-0.0.1.dist-info/WHEEL
verax-0.0.1.dist-info/top_level.txt
verax-0.0.1.dist-info/RECORD
