Metadata-Version: 2.1
Name: verax
Version: 0.0.1
Summary: An simple-to-use AI-driven web framework that interprets natural language code to generate and serve dynamic web pages.
Author: Dark25 (Ruben Roy)
Author-email: me@ruben-roy.com
Keywords: ai,webframework,web development,natural language processing,nlp,code generation,dynamic web pages,language interpretation
Classifier: Development Status :: 3 - Alpha
Classifier: Intended Audience :: Developers
Classifier: License :: OSI Approved :: MIT License
Classifier: Programming Language :: Python :: 3
Classifier: Programming Language :: Python :: 3.6
Classifier: Programming Language :: Python :: 3.7
Classifier: Programming Language :: Python :: 3.8
Classifier: Programming Language :: Python :: 3.9
Requires-Python: >=3.6
Requires-Dist: requests
